LICENSE
README.md
pyproject.toml
src/instagrader/__init__.py
src/instagrader.egg-info/PKG-INFO
src/instagrader.egg-info/SOURCES.txt
src/instagrader.egg-info/dependency_links.txt
src/instagrader.egg-info/requires.txt
src/instagrader.egg-info/top_level.txt
src/instagrader/config/__init__.py
src/instagrader/config/operations.py
src/instagrader/library/Grader.py
src/instagrader/library/HomeworkBackend.py
src/instagrader/library/__init__.py
src/instagrader/library/commons.py
src/instagrader/model/Exceptions.py
src/instagrader/model/__init__.py
src/instagrader/model/activity/CreateHomework.py
src/instagrader/model/activity/CreateStudentAccount.py
src/instagrader/model/activity/GetClassGrades.py
src/instagrader/model/activity/GetHomework.py
src/instagrader/model/activity/GetStudentAccount.py
src/instagrader/model/activity/GetStudentGrades.py
src/instagrader/model/activity/GradeSubmission.py
src/instagrader/model/activity/Payload.py
src/instagrader/model/activity/ResetStudentPassword.py
src/instagrader/model/activity/SendStudentPasswordResetCode.py
src/instagrader/model/activity/UpdateHomework.py
src/instagrader/model/activity/__init__.py
src/instagrader/model/db/GradeBookItem.py
src/instagrader/model/db/Homework.py
src/instagrader/model/db/PasswordResetCode.py
src/instagrader/model/db/StudentAccount.py
src/instagrader/model/db/SubmissionsItem.py
src/instagrader/model/db/TeacherAccount.py
src/instagrader/model/db/__init__.py